electric_barometer/__init__.py
electric_barometer-0.2.5.dist-info/licenses/LICENSE
electric_barometer-0.2.5.dist-info/METADATA
electric_barometer-0.2.5.dist-info/WHEEL
electric_barometer-0.2.5.dist-info/top_level.txt
electric_barometer-0.2.5.dist-info/RECORD
