Metadata-Version: 2.4
Name: electric-barometer
Version: 0.2.5
Summary: Umbrella package for the Electric Barometer ecosystem (metrics, evaluation, features, adapters, and related tooling).
Author-email: "Kyle Corrie (Economistician)" <kcorrie@economistician.com>
License-Expression: BSD-3-Clause
Project-URL: Homepage, https://github.com/Economistician/electric-barometer
Project-URL: Repository, https://github.com/Economistician/electric-barometer
Project-URL: Issues, https://github.com/Economistician/electric-barometer/issues
Project-URL: Documentation, https://economistician.github.io/eb-docs/
Keywords: forecasting,operations,evaluation,metrics,features,time-series
Classifier: Development Status :: 3 - Alpha
Classifier: Intended Audience :: Developers
Classifier: Intended Audience :: Science/Research
Classifier: Programming Language :: Python :: 3
Classifier: Programming Language :: Python :: 3.10
Classifier: Programming Language :: Python :: 3.11
Classifier: Programming Language :: Python :: 3.12
Classifier: Operating System :: OS Independent
Requires-Python: >=3.10
License-File: LICENSE
Requires-Dist: eb-metrics<0.3,>=0.2
Requires-Dist: eb-evaluation<0.3,>=0.2
Requires-Dist: eb-adapters<0.3,>=0.2
Requires-Dist: eb-features<0.3,>=0.2
Provides-Extra: test
Requires-Dist: pytest>=8.0; extra == "test"
Provides-Extra: dev
Requires-Dist: pytest>=8.0; extra == "dev"
Requires-Dist: pytest-cov>=5.0; extra == "dev"
Provides-Extra: metrics
Requires-Dist: eb-metrics<0.3,>=0.2; extra == "metrics"
Provides-Extra: evaluation
Requires-Dist: eb-evaluation<0.3,>=0.2; extra == "evaluation"
Provides-Extra: adapters
Requires-Dist: eb-adapters<0.3,>=0.2; extra == "adapters"
Provides-Extra: features
Requires-Dist: eb-features<0.3,>=0.2; extra == "features"
Provides-Extra: sklearn
Requires-Dist: eb-metrics[sklearn]<0.3,>=0.2; extra == "sklearn"
Provides-Extra: tf
Requires-Dist: eb-metrics[tf]<0.3,>=0.2; extra == "tf"
Provides-Extra: all
Requires-Dist: electric-barometer[metrics]; extra == "all"
Requires-Dist: electric-barometer[evaluation]; extra == "all"
Requires-Dist: electric-barometer[adapters]; extra == "all"
Requires-Dist: electric-barometer[features]; extra == "all"
Requires-Dist: electric-barometer[sklearn]; extra == "all"
Requires-Dist: electric-barometer[tf]; extra == "all"
Dynamic: license-file
